mlxengine/__init__.py
mlxengine/main.py
mlxengine/routers.py
mlxengine/chat/__init__.py
mlxengine/chat/router.py
mlxengine/chat/schema.py
mlxengine/chat/text_models.py
mlxengine/chat/mlx/__init__.py
mlxengine/chat/mlx/mlx_model.py
mlxengine/chat/mlx/models.py
mlxengine/chat/mlx/outlines_logits_processor.py
mlxengine/chat/mlx/prompt_cache.py
mlxengine/chat/mlx/stop_tokens_checker.py
mlxengine/chat/mlx/tools/__init__.py
mlxengine/chat/mlx/tools/chat_tokenizer.py
mlxengine/chat/mlx/tools/hugging_face.py
mlxengine/chat/mlx/tools/llama3.py
mlxengine/chat/mlx/tools/mistral.py
mlxengine/chat/mlx/tools/utils.py
mlxengine/chat/models/__init__.py
mlxengine/chat/models/models.py
mlxengine/chat/models/models_service.py
mlxengine/chat/models/schema.py
mlxengine/images/__init__.py
mlxengine/images/images.py
mlxengine/images/images_service.py
mlxengine/images/schema.py
mlxengine/middleware/logging.py
mlxengine/stt/__init__.py
mlxengine/stt/schema.py
mlxengine/stt/stt.py
mlxengine/stt/whisper_model.py
mlxengine/tts/__init__.py
mlxengine/tts/schema.py
mlxengine/tts/tts.py
mlxengine/tts/tts_service.py
mlxengine/utils/logger.py
mlxengine/utils/serialization.py
mlxengine-0.0.4.dist-info/METADATA
mlxengine-0.0.4.dist-info/WHEEL
mlxengine-0.0.4.dist-info/entry_points.txt
mlxengine-0.0.4.dist-info/RECORD
